t_ragx/__init__.py
t_ragx/main.py
t_ragx/models/API_Model.py
t_ragx/models/AggregationModel.py
t_ragx/models/BaseModel.py
t_ragx/models/InternLM2Model.py
t_ragx/models/LangDetectModel.py
t_ragx/models/LlamaCppPythonModel.py
t_ragx/models/MistralModel.py
t_ragx/models/OllamaModel.py
t_ragx/models/OpenAIModel.py
t_ragx/models/__init__.py
t_ragx/models/_utils.py
t_ragx/models/constants.py
t_ragx/processors/BaseInputProcessor.py
t_ragx/processors/ElasticInputProcessor.py
t_ragx/processors/__init__.py
t_ragx/processors/_utils.py
t_ragx/processors/constants.py
t_ragx/scripts/__init__.py
t_ragx/scripts/build_demo_elastic_memory_index.py
t_ragx/utils/__init__.py
t_ragx/utils/elastic.py
t_ragx/utils/helper.py
t_ragx/utils/heuristic.py
t_ragx/utils/logger.py
t_ragx-0.1.2.dist-info/LICENSE
t_ragx-0.1.2.dist-info/METADATA
t_ragx-0.1.2.dist-info/WHEEL
t_ragx-0.1.2.dist-info/top_level.txt
t_ragx-0.1.2.dist-info/RECORD
