Metadata-Version: 2.1
Name: t_ragx
Version: 0.1.2
Summary: Enhancing translation with RAG-powered large language models
Home-page: https://github.com/rayliuca/T-Ragx
Author: Ray Liu
License: MIT
Project-URL: Bug Reports, https://github.com/rayliuca/T-Ragx/issues
Project-URL: Source, https://github.com/rayliuca/T-Ragx
Keywords: machine-translation,computer-aided-translation,computer-assisted-translation,rag,retrieval-augmented-generation,large-language-models,llm
License-File: LICENSE
Requires-Dist: transformers>=4.38
Requires-Dist: elasticsearch
Requires-Dist: OpenCC
Requires-Dist: levenshtein
Requires-Dist: unbabel-comet>=2.2.1
